dioptra/__init__.py
dioptra/inference/__init__.py
dioptra/inference/inference_runner.py
dioptra/inference/tf/__init__.py
dioptra/inference/tf/tf_runner.py
dioptra/inference/torch/__init__.py
dioptra/inference/torch/torch_runner.py
dioptra/lake/__init__.py
dioptra/lake/datasets.py
dioptra/lake/utils.py
dioptra/lake/torch/__init__.py
dioptra/lake/torch/object_store_datasets.py
dioptra/miners/__init__.py
dioptra/miners/activation_miner.py
dioptra/miners/badge_miner.py
dioptra/miners/base_miner.py
dioptra/miners/coreset_miner.py
dioptra/miners/entropy_miner.py
dioptra/miners/knn_miner.py
dioptra/miners/random_miner.py
dioptra/miners/variance_miner.py
dioptra/miners/weighted_entropy_miner.py
dioptra/ssl/__init__.py
dioptra/ssl/fast_siam.py
dioptra-1.0.29.dist-info/LICENSE.md
dioptra-1.0.29.dist-info/METADATA
dioptra-1.0.29.dist-info/WHEEL
dioptra-1.0.29.dist-info/top_level.txt
dioptra-1.0.29.dist-info/RECORD
