Metadata-Version: 2.1
Name: dioptra
Version: 1.0.29
Summary: Client library to log data to Dioptra API
Home-page: https://github.com/dioptra-ai/collector-py
Author: dioptra.ai
Author-email: info@dioptra.ai
License: BSD
Project-URL: dioptra.ai, https://www.dioptra.ai
Keywords: dioptra
Platform: UNKNOWN
Classifier: Development Status :: 3 - Alpha
Classifier: Intended Audience :: Developers
Classifier: Programming Language :: Python :: 3.5
Classifier: Programming Language :: Python :: 3.6
Classifier: Programming Language :: Python :: 3.7
Classifier: Programming Language :: Python :: 3.8
Requires-Python: >=3.5.3
Requires-Dist: schema (>=0.7.4)
Requires-Dist: requests (>=2.25.0)
Requires-Dist: requests-futures (>=1.0.0)
Requires-Dist: tqdm (>=4.60.0)
Requires-Dist: boto3 (>=1.18.0)
Requires-Dist: fire (>=0.4.0)
Requires-Dist: orjson (>=3.6.4)
Requires-Dist: smart-open (>=5.2.1)
Requires-Dist: python-dateutil (>=2.8.2)
Requires-Dist: mgzip (==0.2.1)
Requires-Dist: pandas (>=1.2.0)
Requires-Dist: lz4 (>=3.1.3)
Requires-Dist: Pillow (>=7.0.0)
Requires-Dist: google-cloud-storage (==2.7.0)
Requires-Dist: pyyaml (>=5.4.1)
Requires-Dist: lightly
